Metadata-Version: 2.1
Name: botsynthesis
Version: 4.0.1
Summary: Protein Sequence Optimizer
Home-page: https://github.com/ArsenicMeatball/BOTS_development
Author: Jean-David Rousseau
Author-email: arsenicmeatball@yahoo.com
License: LICENSE.md
Platform: UNKNOWN
License-File: LICENSE.md
Requires-Dist: python-codon-tables
Requires-Dist: biopython
